sysbox/__init__.py
sysbox/base.py
sysbox/const.py
sysbox/docker.py
sysbox/kubernetes.py
sysbox/session.py
sysbox/utils.py
tests/__init__.py
tests/test_session.py
sysbox-0.1.2.dist-info/LICENSE
sysbox-0.1.2.dist-info/METADATA
sysbox-0.1.2.dist-info/WHEEL
sysbox-0.1.2.dist-info/top_level.txt
sysbox-0.1.2.dist-info/RECORD
