Metadata-Version: 2.1
Name: sysbox
Version: 0.1.2
Summary: Lightweight and portable sandbox runtime (code interpreter) Python library
Home-page: https://github.com/vndee/sysbox
Author: Mark Powers
Author-email: mpoweru@lifsys.com
Classifier: Development Status :: 3 - Alpha
Classifier: Intended Audience :: Developers
Classifier: License :: OSI Approved :: MIT License
Classifier: Operating System :: OS Independent
Classifier: Programming Language :: Python :: 3
Classifier: Programming Language :: Python :: 3.7
Classifier: Programming Language :: Python :: 3.8
Classifier: Programming Language :: Python :: 3.9
Classifier: Programming Language :: Python :: 3.10
Classifier: Programming Language :: Python :: 3.11
Requires-Python: >=3.7
License-File: LICENSE
Requires-Dist: docker>=7.1.0
Requires-Dist: kubernetes>=30.1.0
